runpythonpackage/__init__.py
runpythonpackage/__main__.py
runpythonpackagepythonplayer123-0.2.0.dist-info/METADATA
runpythonpackagepythonplayer123-0.2.0.dist-info/WHEEL
runpythonpackagepythonplayer123-0.2.0.dist-info/entry_points.txt
runpythonpackagepythonplayer123-0.2.0.dist-info/RECORD
